{
  "table_name": "chats",
  "row_count": 5,
  "exported_at": "2025-08-29T23:08:49.138Z",
  "data": [
    {
      "id": "e27a5a0d-7536-43ce-9fd4-7e7d23ba4f66",
      "type": "direct",
      "name": "Email User",
      "avatar_url": null,
      "last_message_id": null,
      "last_message_time": null,
      "created_at": "2025-08-27T20:46:55.520962+00:00",
      "updated_at": "2025-08-27T20:46:55.520962+00:00",
      "created_by": null
    },
    {
      "id": "5184cd13-9930-49ca-a556-fbdea2e4fd00",
      "type": "direct",
      "name": "Email User",
      "avatar_url": null,
      "last_message_id": null,
      "last_message_time": null,
      "created_at": "2025-08-27T20:47:06.014957+00:00",
      "updated_at": "2025-08-27T20:47:06.014957+00:00",
      "created_by": null
    },
    {
      "id": "db183efe-93b4-4baa-8cd4-808270babee1",
      "type": "direct",
      "name": "Email User",
      "avatar_url": null,
      "last_message_id": null,
      "last_message_time": null,
      "created_at": "2025-08-27T20:52:03.078846+00:00",
      "updated_at": "2025-08-27T20:52:03.078846+00:00",
      "created_by": null
    },
    {
      "id": "34194ff1-24bd-4611-962c-91ead50a27b0",
      "type": "direct",
      "name": "Email User",
      "avatar_url": null,
      "last_message_id": null,
      "last_message_time": null,
      "created_at": "2025-08-27T20:52:05.14133+00:00",
      "updated_at": "2025-08-27T20:52:05.14133+00:00",
      "created_by": null
    },
    {
      "id": "c09c58bd-97dd-4360-aa8d-9ae84f1a8256",
      "type": "direct",
      "name": "Email User",
      "avatar_url": null,
      "last_message_id": null,
      "last_message_time": null,
      "created_at": "2025-08-27T20:52:06.063302+00:00",
      "updated_at": "2025-08-27T20:52:06.063302+00:00",
      "created_by": null
    }
  ]
}